<?xml version="1.0" encoding="UTF-8"?>
<metadata>
  <identifier>bmshri.sankranthi0000srin.8k8.421.san</identifier>
  <camera>Sony Alpha-A6000 (Control)</camera>
  <collection>ServantsOfKnowledge</collection>
  <collection>JaiGyan</collection>
  <collection_set>ServantsOfKnowledge</collection_set>
  <contributor>Servants of Knowledge</contributor>
  <creator>ಶ್ರೀನಿವಾಸ್</creator>
  <date>1969</date>
  <language>kan</language>
  <mediatype>texts</mediatype>
  <operator>carl+sok_maa@media.org</operator>
  <page-progression>lr</page-progression>
  <partner>Kahle/Austin - Indian Academy of Sciences</partner>
  <publisher>ಜೀವನ ಕರ್ಯಾಲಯ ಟ್ರಸ್ಟ್</publisher>
  <rcs_key>24685</rcs_key>
  <repub_state>19</repub_state>
  <scanner>ttscribe7.sok.archive.org</scanner>
  <scanningcenter>tt_sok</scanningcenter>
  <title>ಸಂಕ್ರಾಂತಿ</title>
  <tts_version>5.4-initial-25-ga9c0370c</tts_version>
  <uploader>ttscribe7.sok@archive.org</uploader>
  <publicdate>2023-02-24 05:54:27</publicdate>
  <imagecount>94</imagecount>
  <scandate>20230224062333</scandate>
  <ppi>360</ppi>
  <republisher_operator>associate-josephine-ochavo@archive.org</republisher_operator>
  <republisher_date>20230227205043</republisher_date>
  <republisher_time>323</republisher_time>
  <foldoutcount>0</foldoutcount>
  <identifier-access>http://archive.org/details/bmshri.sankranthi0000srin.8k8.421.san</identifier-access>
  <identifier-ark>ark:/13960/s23tc1478hg</identifier-ark>
  <ocr>tesseract 5.3.0-3-g9920</ocr>
  <ocr_parameters>-l kan+Kannada</ocr_parameters>
  <ocr_module_version>0.0.19</ocr_module_version>
  <ocr_detected_script>Kannada</ocr_detected_script>
  <ocr_detected_script_conf>0.9569</ocr_detected_script_conf>
  <ocr_detected_lang>kn</ocr_detected_lang>
  <ocr_detected_lang_conf>1.0000</ocr_detected_lang_conf>
  <pdf_module_version>0.0.22</pdf_module_version>
  <addeddate>2023-02-27 13:21:37</addeddate>
  <scanfee>0;4;4</scanfee>
  <invoice>1661</invoice>
  <sponsordate>20230228</sponsordate>
  <alt_publisher>Jeevana Karyalaya Trust</alt_publisher>
  <source>https://www.bmshri.org/</source>
  <subject>ಕನ್ನಡ ಸಾಹಿತ್ಯ; ಬಿ.ಎಂ.ಶ್ರೀ ಸಂಚಯ</subject>
  <description>ಈ ಪುಸ್ತಕವನ್ನು ಎಲ್ಲ ಕನ್ನಡಿಗರಿಗೆ ಸಾಹಿತ್ಯವನ್ನು ಲಭ್ಯವಾಗಿಸುವ ಆಶಯದೊಂದಿಗೆ, ಬಿ. ಎಂ. ಶ್ರೀ ಪ್ರತಿಷ್ಠಾನದ ಸಹಯೋಗದೊಂದಿಗೆ -ಸಂಚಯದ ಕನ್ನಡ ಡಿಜಿಟಲೀಕರಣ ಯೊಜನೆ ಅಡಿ, ಡಿಜಿಟಲೀಕರಿಸಲಾಗಿದೆ/ಸಂರಕ್ಷಿಸಲಾಗಿದೆ. ನಮ್ಮ ಯೋಜನೆಯ ಬಗ್ಗೆ ಹೆಚ್ಚಿನ ಮಾಹಿತಿ ಇಲ್ಲಿ ಲಭ್ಯವಿದೆ - https://sanchaya.org/project/kannada-digitization-project/</description>
  <alt_title>Sankranthi</alt_title>
  <year>1969</year>
  <alt_creator>Srinivas</alt_creator>
</metadata>
